minimigrate.py
minimigrate-0.1.1.dist-info/DESCRIPTION.rst
minimigrate-0.1.1.dist-info/METADATA
minimigrate-0.1.1.dist-info/RECORD
minimigrate-0.1.1.dist-info/WHEEL
minimigrate-0.1.1.dist-info/entry_points.txt
minimigrate-0.1.1.dist-info/metadata.json
minimigrate-0.1.1.dist-info/top_level.txt
