Metadata-Version: 2.0
Name: minimigrate
Version: 0.1.1
Summary: A simple schema migration tool
Home-page: https://github.com/jrdmcgr/minimigrate
Author: Jared McGuire
Author-email: jrdmcgr@gmail.com
License: MIT
Keywords: schema migration
Platform: UNKNOWN
Classifier: Development Status :: 3 - Alpha
Classifier: Intended Audience :: Developers
Classifier: License :: OSI Approved :: MIT License
Classifier: Programming Language :: Python :: 2.7
Classifier: Topic :: Utilities
Requires-Dist: pathlib
Requires-Dist: sqlalchemy
Provides-Extra: test
Requires-Dist: coverage; extra == 'test'
Requires-Dist: nose; extra == 'test'
